Kannadafy/__init__.py
Kannadafy/__main__.py
Kannadafy/cli.py
Kannadafy/core.py
Kannadafy/kannadafy.py
Kannadafy/utils/__init__.py
Kannadafy/utils/mapping.py
Kannadafy/utils/text_obfuscation.py
Kannadafy/utils/validation.py
kannadafy-2.0.9.dist-info/METADATA
kannadafy-2.0.9.dist-info/WHEEL
kannadafy-2.0.9.dist-info/entry_points.txt
kannadafy-2.0.9.dist-info/top_level.txt
kannadafy-2.0.9.dist-info/RECORD
