Metadata-Version: 2.4
Name: Kannadafy
Version: 2.0.9
Summary: Python code obfuscator using Kannada script and text-based mapping
Home-page: https://github.com/mithun50/Kannadafy
Author: MithunGowda.B, Manvanth.
Author-email: mithungowda.b7411@gmail.com, appuka1431@gmail.com
Project-URL: Documentation, https://github.com/mithun50/Kannadafy/blob/main/README.md
Project-URL: Source, https://github.com/mithun50/Kannadafy
Project-URL: Tracker, https://github.com/mithun50/Kannadafy/issues
Keywords: python obfuscator kannada script security text-based
Classifier: Programming Language :: Python :: 3
Classifier: Programming Language :: Python :: 3.6
Classifier: Programming Language :: Python :: 3.7
Classifier: Programming Language :: Python :: 3.8
Classifier: Programming Language :: Python :: 3.9
Classifier: Programming Language :: Python :: 3.10
Classifier: License :: OSI Approved :: MIT License
Classifier: Operating System :: OS Independent
Classifier: Intended Audience :: Developers
Classifier: Topic :: Software Development :: Libraries :: Python Modules
Classifier: Topic :: Security :: Cryptography
Requires-Python: >=3.6
Requires-Dist: pyyaml>=5.1
Dynamic: author
Dynamic: author-email
Dynamic: classifier
Dynamic: description
Dynamic: description-content-type
Dynamic: home-page
Dynamic: keywords
Dynamic: project-url
Dynamic: requires-dist
Dynamic: requires-python
Dynamic: summary
